devatrans/__init__.py
devatrans/devatrans.py
devatrans/prereq.py
devatrans/scheme.py
devatrans/test.py
devatrans/data/hk_back_trans.json
devatrans/data/hk_trans.json
devatrans/data/iast_back_trans.json
devatrans/data/iast_trans.json
devatrans/data/itrans_back_trans.json
devatrans/data/itrans_trans.json
devatrans/data/sanskrit.json
devatrans/data/velthuis_back_trans.json
devatrans/data/velthuis_trans.json
devatrans-5.0.1.dist-info/LICENSE.md
devatrans-5.0.1.dist-info/METADATA
devatrans-5.0.1.dist-info/WHEEL
devatrans-5.0.1.dist-info/top_level.txt
devatrans-5.0.1.dist-info/RECORD
