Metadata-Version: 2.1
Name: devatrans
Version: 5.0.1
Summary: devatrans is an easy-to-use tool for transliteration,
Home-page: https://github.com/RaviTeja51/devatrans.git
Author: Ravi Teja
Author-email: ravitejatasubilli@gmail.com
License: Apache
Platform: UNKNOWN
Classifier: Development Status :: 5 - Production/Stable
Classifier: License :: OSI Approved :: Apache Software License
Classifier: Programming Language :: Python
Classifier: Programming Language :: Python :: 3.5
Classifier: Programming Language :: Python :: 3.6
Classifier: Programming Language :: Python :: 3.7
Classifier: Topic :: Software Development :: Libraries
Classifier: Topic :: Software Development :: Libraries :: Python Modules
Classifier: Intended Audience :: Developers
Requires-Python: >=3.5
